{
  "date": "2026-04-18",
  "todayPlan": {
    "priorities": [
      "Wake up 6:30 to 7 am"
    ],
    "wakeTime": "06:50",
    "focus": "deep",
    "notes": "I will remove social media and goo fully focussed",
    "date": "2026-04-18",
    "ts": "11:56 PM"
  },
  "recentPlans": [
    {
      "priorities": [
        "Wake up 6:30 to 7 am"
      ],
      "wakeTime": "06:50",
      "focus": "deep",
      "notes": "I will remove social media and goo fully focussed",
      "date": "2026-04-18",
      "ts": "11:56 PM"
    }
  ],
  "summary": {
    "totalPlans": 1,
    "hasTodayPlan": true
  }
}